AUTHORS
LICENSE
MANIFEST.in
README
setup.py
nsplist/__init__.py
nsplist/decoder.py
nsplist/scanner.py
nsplist.egg-info/PKG-INFO
nsplist.egg-info/SOURCES.txt
nsplist.egg-info/dependency_links.txt
nsplist.egg-info/top_level.txt