Metadata-Version: 1.1
Name: nsplist
Version: 0.1
Summary: A parser for NeXTSTEP-style plists.
Home-page: http://fireteam.net
Author: Fireteam Ltd.
Author-email: info@fireteam.net
License: MIT License
Platform: UNKNOWN
Classifier: Intended Audience :: Developers
Classifier: Development Status :: 5 - Production/Stable
Classifier: License :: OSI Approved :: MIT License
Classifier: Programming Language :: Python
Classifier: Programming Language :: Python :: 2
Classifier: Programming Language :: Python :: 2.7
